{
  "ai_education_design": {
    "translation_status": {
      "zhTW": {
        "total_fields": 20,
        "translated_fields": 16,
        "untranslated_fields": 4,
        "translation_rate": 80.0
      },
      "zhCN": {
        "total_fields": 20,
        "translated_fields": 16,
        "untranslated_fields": 4,
        "translation_rate": 80.0
      },
      "ja": {
        "total_fields": 20,
        "translated_fields": 16,
        "untranslated_fields": 4,
        "translation_rate": 80.0
      },
      "ko": {
        "total_fields": 20,
        "translated_fields": 16,
        "untranslated_fields": 4,
        "translation_rate": 80.0
      },
      "es": {
        "total_fields": 20,
        "translated_fields": 16,
        "untranslated_fields": 4,
        "translation_rate": 80.0
      },
      "fr": {
        "total_fields": 20,
        "translated_fields": 16,
        "untranslated_fields": 4,
        "translation_rate": 80.0
      },
      "de": {
        "total_fields": 20,
        "translated_fields": 16,
        "untranslated_fields": 4,
        "translation_rate": 80.0
      },
      "it": {
        "total_fields": 20,
        "translated_fields": 16,
        "untranslated_fields": 4,
        "translation_rate": 80.0
      },
      "pt": {
        "total_fields": 20,
        "translated_fields": 16,
        "untranslated_fields": 4,
        "translation_rate": 80.0
      },
      "ru": {
        "total_fields": 20,
        "translated_fields": 16,
        "untranslated_fields": 4,
        "translation_rate": 80.0
      },
      "ar": {
        "total_fields": 20,
        "translated_fields": 16,
        "untranslated_fields": 4,
        "translation_rate": 80.0
      },
      "th": {
        "total_fields": 20,
        "translated_fields": 16,
        "untranslated_fields": 4,
        "translation_rate": 80.0
      },
      "id": {
        "total_fields": 20,
        "translated_fields": 16,
        "untranslated_fields": 4,
        "translation_rate": 80.0
      }
    },
    "untranslated_fields": {
      "zhTW": [
        "scenario_info.title",
        "scenario_info.description",
        "scenario_info.prerequisites",
        "scenario_info.learning_objectives"
      ],
      "zhCN": [
        "scenario_info.title",
        "scenario_info.description",
        "scenario_info.prerequisites",
        "scenario_info.learning_objectives"
      ],
      "ja": [
        "scenario_info.title",
        "scenario_info.description",
        "scenario_info.prerequisites",
        "scenario_info.learning_objectives"
      ],
      "ko": [
        "scenario_info.title",
        "scenario_info.description",
        "scenario_info.prerequisites",
        "scenario_info.learning_objectives"
      ],
      "es": [
        "scenario_info.title",
        "scenario_info.description",
        "scenario_info.prerequisites",
        "scenario_info.learning_objectives"
      ],
      "fr": [
        "scenario_info.title",
        "scenario_info.description",
        "scenario_info.prerequisites",
        "scenario_info.learning_objectives"
      ],
      "de": [
        "scenario_info.title",
        "scenario_info.description",
        "scenario_info.prerequisites",
        "scenario_info.learning_objectives"
      ],
      "it": [
        "scenario_info.title",
        "scenario_info.description",
        "scenario_info.prerequisites",
        "scenario_info.learning_objectives"
      ],
      "pt": [
        "scenario_info.title",
        "scenario_info.description",
        "scenario_info.prerequisites",
        "scenario_info.learning_objectives"
      ],
      "ru": [
        "scenario_info.title",
        "scenario_info.description",
        "scenario_info.prerequisites",
        "scenario_info.learning_objectives"
      ],
      "ar": [
        "scenario_info.title",
        "scenario_info.description",
        "scenario_info.prerequisites",
        "scenario_info.learning_objectives"
      ],
      "th": [
        "scenario_info.title",
        "scenario_info.description",
        "scenario_info.prerequisites",
        "scenario_info.learning_objectives"
      ],
      "id": [
        "scenario_info.title",
        "scenario_info.description",
        "scenario_info.prerequisites",
        "scenario_info.learning_objectives"
      ]
    },
    "missing_files": []
  },
  "ai_job_search": {
    "translation_status": {
      "zhTW": {
        "total_fields": 24,
        "translated_fields": 20,
        "untranslated_fields": 4,
        "translation_rate": 83.3
      },
      "zhCN": {
        "total_fields": 24,
        "translated_fields": 4,
        "untranslated_fields": 20,
        "translation_rate": 16.7
      },
      "ja": {
        "total_fields": 24,
        "translated_fields": 20,
        "untranslated_fields": 4,
        "translation_rate": 83.3
      },
      "ko": {
        "total_fields": 24,
        "translated_fields": 20,
        "untranslated_fields": 4,
        "translation_rate": 83.3
      },
      "es": {
        "total_fields": 24,
        "translated_fields": 20,
        "untranslated_fields": 4,
        "translation_rate": 83.3
      },
      "fr": {
        "total_fields": 24,
        "translated_fields": 20,
        "untranslated_fields": 4,
        "translation_rate": 83.3
      },
      "de": {
        "total_fields": 24,
        "translated_fields": 20,
        "untranslated_fields": 4,
        "translation_rate": 83.3
      },
      "it": {
        "total_fields": 24,
        "translated_fields": 20,
        "untranslated_fields": 4,
        "translation_rate": 83.3
      },
      "pt": {
        "total_fields": 24,
        "translated_fields": 4,
        "untranslated_fields": 20,
        "translation_rate": 16.7
      },
      "ru": {
        "total_fields": 24,
        "translated_fields": 20,
        "untranslated_fields": 4,
        "translation_rate": 83.3
      },
      "ar": {
        "total_fields": 24,
        "translated_fields": 4,
        "untranslated_fields": 20,
        "translation_rate": 16.7
      },
      "th": {
        "total_fields": 24,
        "translated_fields": 4,
        "untranslated_fields": 20,
        "translation_rate": 16.7
      },
      "id": {
        "total_fields": 24,
        "translated_fields": 4,
        "untranslated_fields": 20,
        "translation_rate": 16.7
      }
    },
    "untranslated_fields": {
      "zhTW": [
        "scenario_info.title",
        "scenario_info.description",
        "scenario_info.prerequisites",
        "scenario_info.learning_objectives"
      ],
      "zhCN": [
        "tasks[0].title",
        "tasks[0].description",
        "tasks[0].instructions",
        "tasks[0].expected_outcome",
        "tasks[1].title",
        "tasks[1].description",
        "tasks[1].instructions",
        "tasks[1].expected_outcome",
        "tasks[2].title",
        "tasks[2].description",
        "tasks[2].instructions",
        "tasks[2].expected_outcome",
        "tasks[3].title",
        "tasks[3].description",
        "tasks[3].instructions",
        "tasks[3].expected_outcome",
        "tasks[4].title",
        "tasks[4].description",
        "tasks[4].instructions",
        "tasks[4].expected_outcome"
      ],
      "ja": [
        "scenario_info.title",
        "scenario_info.description",
        "scenario_info.prerequisites",
        "scenario_info.learning_objectives"
      ],
      "ko": [
        "scenario_info.title",
        "scenario_info.description",
        "scenario_info.prerequisites",
        "scenario_info.learning_objectives"
      ],
      "es": [
        "scenario_info.title",
        "scenario_info.description",
        "scenario_info.prerequisites",
        "scenario_info.learning_objectives"
      ],
      "fr": [
        "scenario_info.title",
        "scenario_info.description",
        "scenario_info.prerequisites",
        "scenario_info.learning_objectives"
      ],
      "de": [
        "scenario_info.title",
        "scenario_info.description",
        "scenario_info.prerequisites",
        "scenario_info.learning_objectives"
      ],
      "it": [
        "scenario_info.title",
        "scenario_info.description",
        "scenario_info.prerequisites",
        "scenario_info.learning_objectives"
      ],
      "pt": [
        "tasks[0].title",
        "tasks[0].description",
        "tasks[0].instructions",
        "tasks[0].expected_outcome",
        "tasks[1].title",
        "tasks[1].description",
        "tasks[1].instructions",
        "tasks[1].expected_outcome",
        "tasks[2].title",
        "tasks[2].description",
        "tasks[2].instructions",
        "tasks[2].expected_outcome",
        "tasks[3].title",
        "tasks[3].description",
        "tasks[3].instructions",
        "tasks[3].expected_outcome",
        "tasks[4].title",
        "tasks[4].description",
        "tasks[4].instructions",
        "tasks[4].expected_outcome"
      ],
      "ru": [
        "scenario_info.title",
        "scenario_info.description",
        "scenario_info.prerequisites",
        "scenario_info.learning_objectives"
      ],
      "ar": [
        "tasks[0].title",
        "tasks[0].description",
        "tasks[0].instructions",
        "tasks[0].expected_outcome",
        "tasks[1].title",
        "tasks[1].description",
        "tasks[1].instructions",
        "tasks[1].expected_outcome",
        "tasks[2].title",
        "tasks[2].description",
        "tasks[2].instructions",
        "tasks[2].expected_outcome",
        "tasks[3].title",
        "tasks[3].description",
        "tasks[3].instructions",
        "tasks[3].expected_outcome",
        "tasks[4].title",
        "tasks[4].description",
        "tasks[4].instructions",
        "tasks[4].expected_outcome"
      ],
      "th": [
        "tasks[0].title",
        "tasks[0].description",
        "tasks[0].instructions",
        "tasks[0].expected_outcome",
        "tasks[1].title",
        "tasks[1].description",
        "tasks[1].instructions",
        "tasks[1].expected_outcome",
        "tasks[2].title",
        "tasks[2].description",
        "tasks[2].instructions",
        "tasks[2].expected_outcome",
        "tasks[3].title",
        "tasks[3].description",
        "tasks[3].instructions",
        "tasks[3].expected_outcome",
        "tasks[4].title",
        "tasks[4].description",
        "tasks[4].instructions",
        "tasks[4].expected_outcome"
      ],
      "id": [
        "tasks[0].title",
        "tasks[0].description",
        "tasks[0].instructions",
        "tasks[0].expected_outcome",
        "tasks[1].title",
        "tasks[1].description",
        "tasks[1].instructions",
        "tasks[1].expected_outcome",
        "tasks[2].title",
        "tasks[2].description",
        "tasks[2].instructions",
        "tasks[2].expected_outcome",
        "tasks[3].title",
        "tasks[3].description",
        "tasks[3].instructions",
        "tasks[3].expected_outcome",
        "tasks[4].title",
        "tasks[4].description",
        "tasks[4].instructions",
        "tasks[4].expected_outcome"
      ]
    },
    "missing_files": []
  },
  "ai_robotics_development": {
    "translation_status": {
      "zhTW": {
        "total_fields": 16,
        "translated_fields": 12,
        "untranslated_fields": 4,
        "translation_rate": 75.0
      },
      "zhCN": {
        "total_fields": 16,
        "translated_fields": 4,
        "untranslated_fields": 12,
        "translation_rate": 25.0
      },
      "ja": {
        "total_fields": 16,
        "translated_fields": 12,
        "untranslated_fields": 4,
        "translation_rate": 75.0
      },
      "ko": {
        "total_fields": 16,
        "translated_fields": 12,
        "untranslated_fields": 4,
        "translation_rate": 75.0
      },
      "es": {
        "total_fields": 16,
        "translated_fields": 12,
        "untranslated_fields": 4,
        "translation_rate": 75.0
      },
      "fr": {
        "total_fields": 16,
        "translated_fields": 12,
        "untranslated_fields": 4,
        "translation_rate": 75.0
      },
      "de": {
        "total_fields": 16,
        "translated_fields": 12,
        "untranslated_fields": 4,
        "translation_rate": 75.0
      },
      "it": {
        "total_fields": 16,
        "translated_fields": 12,
        "untranslated_fields": 4,
        "translation_rate": 75.0
      },
      "pt": {
        "total_fields": 16,
        "translated_fields": 4,
        "untranslated_fields": 12,
        "translation_rate": 25.0
      },
      "ru": {
        "total_fields": 16,
        "translated_fields": 12,
        "untranslated_fields": 4,
        "translation_rate": 75.0
      },
      "ar": {
        "total_fields": 16,
        "translated_fields": 4,
        "untranslated_fields": 12,
        "translation_rate": 25.0
      },
      "th": {
        "total_fields": 16,
        "translated_fields": 4,
        "untranslated_fields": 12,
        "translation_rate": 25.0
      },
      "id": {
        "total_fields": 16,
        "translated_fields": 4,
        "untranslated_fields": 12,
        "translation_rate": 25.0
      }
    },
    "untranslated_fields": {
      "zhTW": [
        "scenario_info.title",
        "scenario_info.description",
        "scenario_info.prerequisites",
        "scenario_info.learning_objectives"
      ],
      "zhCN": [
        "tasks[0].title",
        "tasks[0].description",
        "tasks[0].instructions",
        "tasks[0].expected_outcome",
        "tasks[1].title",
        "tasks[1].description",
        "tasks[1].instructions",
        "tasks[1].expected_outcome",
        "tasks[2].title",
        "tasks[2].description",
        "tasks[2].instructions",
        "tasks[2].expected_outcome"
      ],
      "ja": [
        "scenario_info.title",
        "scenario_info.description",
        "scenario_info.prerequisites",
        "scenario_info.learning_objectives"
      ],
      "ko": [
        "scenario_info.title",
        "scenario_info.description",
        "scenario_info.prerequisites",
        "scenario_info.learning_objectives"
      ],
      "es": [
        "scenario_info.title",
        "scenario_info.description",
        "scenario_info.prerequisites",
        "scenario_info.learning_objectives"
      ],
      "fr": [
        "scenario_info.title",
        "scenario_info.description",
        "scenario_info.prerequisites",
        "scenario_info.learning_objectives"
      ],
      "de": [
        "scenario_info.title",
        "scenario_info.description",
        "scenario_info.prerequisites",
        "scenario_info.learning_objectives"
      ],
      "it": [
        "scenario_info.title",
        "scenario_info.description",
        "scenario_info.prerequisites",
        "scenario_info.learning_objectives"
      ],
      "pt": [
        "tasks[0].title",
        "tasks[0].description",
        "tasks[0].instructions",
        "tasks[0].expected_outcome",
        "tasks[1].title",
        "tasks[1].description",
        "tasks[1].instructions",
        "tasks[1].expected_outcome",
        "tasks[2].title",
        "tasks[2].description",
        "tasks[2].instructions",
        "tasks[2].expected_outcome"
      ],
      "ru": [
        "scenario_info.title",
        "scenario_info.description",
        "scenario_info.prerequisites",
        "scenario_info.learning_objectives"
      ],
      "ar": [
        "tasks[0].title",
        "tasks[0].description",
        "tasks[0].instructions",
        "tasks[0].expected_outcome",
        "tasks[1].title",
        "tasks[1].description",
        "tasks[1].instructions",
        "tasks[1].expected_outcome",
        "tasks[2].title",
        "tasks[2].description",
        "tasks[2].instructions",
        "tasks[2].expected_outcome"
      ],
      "th": [
        "tasks[0].title",
        "tasks[0].description",
        "tasks[0].instructions",
        "tasks[0].expected_outcome",
        "tasks[1].title",
        "tasks[1].description",
        "tasks[1].instructions",
        "tasks[1].expected_outcome",
        "tasks[2].title",
        "tasks[2].description",
        "tasks[2].instructions",
        "tasks[2].expected_outcome"
      ],
      "id": [
        "tasks[0].title",
        "tasks[0].description",
        "tasks[0].instructions",
        "tasks[0].expected_outcome",
        "tasks[1].title",
        "tasks[1].description",
        "tasks[1].instructions",
        "tasks[1].expected_outcome",
        "tasks[2].title",
        "tasks[2].description",
        "tasks[2].instructions",
        "tasks[2].expected_outcome"
      ]
    },
    "missing_files": []
  },
  "ai_stablecoin_trading": {
    "translation_status": {
      "zhTW": {
        "total_fields": 16,
        "translated_fields": 12,
        "untranslated_fields": 4,
        "translation_rate": 75.0
      },
      "zhCN": {
        "total_fields": 16,
        "translated_fields": 4,
        "untranslated_fields": 12,
        "translation_rate": 25.0
      },
      "ja": {
        "total_fields": 16,
        "translated_fields": 12,
        "untranslated_fields": 4,
        "translation_rate": 75.0
      },
      "ko": {
        "total_fields": 16,
        "translated_fields": 12,
        "untranslated_fields": 4,
        "translation_rate": 75.0
      },
      "es": {
        "total_fields": 16,
        "translated_fields": 12,
        "untranslated_fields": 4,
        "translation_rate": 75.0
      },
      "fr": {
        "total_fields": 16,
        "translated_fields": 12,
        "untranslated_fields": 4,
        "translation_rate": 75.0
      },
      "de": {
        "total_fields": 16,
        "translated_fields": 12,
        "untranslated_fields": 4,
        "translation_rate": 75.0
      },
      "it": {
        "total_fields": 16,
        "translated_fields": 12,
        "untranslated_fields": 4,
        "translation_rate": 75.0
      },
      "pt": {
        "total_fields": 16,
        "translated_fields": 4,
        "untranslated_fields": 12,
        "translation_rate": 25.0
      },
      "ru": {
        "total_fields": 16,
        "translated_fields": 12,
        "untranslated_fields": 4,
        "translation_rate": 75.0
      },
      "ar": {
        "total_fields": 16,
        "translated_fields": 4,
        "untranslated_fields": 12,
        "translation_rate": 25.0
      },
      "th": {
        "total_fields": 16,
        "translated_fields": 4,
        "untranslated_fields": 12,
        "translation_rate": 25.0
      },
      "id": {
        "total_fields": 16,
        "translated_fields": 4,
        "untranslated_fields": 12,
        "translation_rate": 25.0
      }
    },
    "untranslated_fields": {
      "zhTW": [
        "scenario_info.title",
        "scenario_info.description",
        "scenario_info.prerequisites",
        "scenario_info.learning_objectives"
      ],
      "zhCN": [
        "tasks[0].title",
        "tasks[0].description",
        "tasks[0].instructions",
        "tasks[0].expected_outcome",
        "tasks[1].title",
        "tasks[1].description",
        "tasks[1].instructions",
        "tasks[1].expected_outcome",
        "tasks[2].title",
        "tasks[2].description",
        "tasks[2].instructions",
        "tasks[2].expected_outcome"
      ],
      "ja": [
        "scenario_info.title",
        "scenario_info.description",
        "scenario_info.prerequisites",
        "scenario_info.learning_objectives"
      ],
      "ko": [
        "scenario_info.title",
        "scenario_info.description",
        "scenario_info.prerequisites",
        "scenario_info.learning_objectives"
      ],
      "es": [
        "scenario_info.title",
        "scenario_info.description",
        "scenario_info.prerequisites",
        "scenario_info.learning_objectives"
      ],
      "fr": [
        "scenario_info.title",
        "scenario_info.description",
        "scenario_info.prerequisites",
        "scenario_info.learning_objectives"
      ],
      "de": [
        "scenario_info.title",
        "scenario_info.description",
        "scenario_info.prerequisites",
        "scenario_info.learning_objectives"
      ],
      "it": [
        "scenario_info.title",
        "scenario_info.description",
        "scenario_info.prerequisites",
        "scenario_info.learning_objectives"
      ],
      "pt": [
        "tasks[0].title",
        "tasks[0].description",
        "tasks[0].instructions",
        "tasks[0].expected_outcome",
        "tasks[1].title",
        "tasks[1].description",
        "tasks[1].instructions",
        "tasks[1].expected_outcome",
        "tasks[2].title",
        "tasks[2].description",
        "tasks[2].instructions",
        "tasks[2].expected_outcome"
      ],
      "ru": [
        "scenario_info.title",
        "scenario_info.description",
        "scenario_info.prerequisites",
        "scenario_info.learning_objectives"
      ],
      "ar": [
        "tasks[0].title",
        "tasks[0].description",
        "tasks[0].instructions",
        "tasks[0].expected_outcome",
        "tasks[1].title",
        "tasks[1].description",
        "tasks[1].instructions",
        "tasks[1].expected_outcome",
        "tasks[2].title",
        "tasks[2].description",
        "tasks[2].instructions",
        "tasks[2].expected_outcome"
      ],
      "th": [
        "tasks[0].title",
        "tasks[0].description",
        "tasks[0].instructions",
        "tasks[0].expected_outcome",
        "tasks[1].title",
        "tasks[1].description",
        "tasks[1].instructions",
        "tasks[1].expected_outcome",
        "tasks[2].title",
        "tasks[2].description",
        "tasks[2].instructions",
        "tasks[2].expected_outcome"
      ],
      "id": [
        "tasks[0].title",
        "tasks[0].description",
        "tasks[0].instructions",
        "tasks[0].expected_outcome",
        "tasks[1].title",
        "tasks[1].description",
        "tasks[1].instructions",
        "tasks[1].expected_outcome",
        "tasks[2].title",
        "tasks[2].description",
        "tasks[2].instructions",
        "tasks[2].expected_outcome"
      ]
    },
    "missing_files": []
  },
  "high_school_climate_change": {
    "translation_status": {
      "zhTW": {
        "total_fields": 20,
        "translated_fields": 16,
        "untranslated_fields": 4,
        "translation_rate": 80.0
      },
      "zhCN": {
        "total_fields": 20,
        "translated_fields": 4,
        "untranslated_fields": 16,
        "translation_rate": 20.0
      },
      "ja": {
        "total_fields": 20,
        "translated_fields": 16,
        "untranslated_fields": 4,
        "translation_rate": 80.0
      },
      "ko": {
        "total_fields": 20,
        "translated_fields": 16,
        "untranslated_fields": 4,
        "translation_rate": 80.0
      },
      "es": {
        "total_fields": 20,
        "translated_fields": 16,
        "untranslated_fields": 4,
        "translation_rate": 80.0
      },
      "fr": {
        "total_fields": 20,
        "translated_fields": 16,
        "untranslated_fields": 4,
        "translation_rate": 80.0
      },
      "de": {
        "total_fields": 20,
        "translated_fields": 16,
        "untranslated_fields": 4,
        "translation_rate": 80.0
      },
      "it": {
        "total_fields": 20,
        "translated_fields": 16,
        "untranslated_fields": 4,
        "translation_rate": 80.0
      },
      "pt": {
        "total_fields": 20,
        "translated_fields": 4,
        "untranslated_fields": 16,
        "translation_rate": 20.0
      },
      "ru": {
        "total_fields": 20,
        "translated_fields": 16,
        "untranslated_fields": 4,
        "translation_rate": 80.0
      },
      "ar": {
        "total_fields": 20,
        "translated_fields": 4,
        "untranslated_fields": 16,
        "translation_rate": 20.0
      },
      "th": {
        "total_fields": 20,
        "translated_fields": 4,
        "untranslated_fields": 16,
        "translation_rate": 20.0
      },
      "id": {
        "total_fields": 20,
        "translated_fields": 4,
        "untranslated_fields": 16,
        "translation_rate": 20.0
      }
    },
    "untranslated_fields": {
      "zhTW": [
        "scenario_info.title",
        "scenario_info.description",
        "scenario_info.prerequisites",
        "scenario_info.learning_objectives"
      ],
      "zhCN": [
        "tasks[0].title",
        "tasks[0].description",
        "tasks[0].instructions",
        "tasks[0].expected_outcome",
        "tasks[1].title",
        "tasks[1].description",
        "tasks[1].instructions",
        "tasks[1].expected_outcome",
        "tasks[2].title",
        "tasks[2].description",
        "tasks[2].instructions",
        "tasks[2].expected_outcome",
        "tasks[3].title",
        "tasks[3].description",
        "tasks[3].instructions",
        "tasks[3].expected_outcome"
      ],
      "ja": [
        "scenario_info.title",
        "scenario_info.description",
        "scenario_info.prerequisites",
        "scenario_info.learning_objectives"
      ],
      "ko": [
        "scenario_info.title",
        "scenario_info.description",
        "scenario_info.prerequisites",
        "scenario_info.learning_objectives"
      ],
      "es": [
        "scenario_info.title",
        "scenario_info.description",
        "scenario_info.prerequisites",
        "scenario_info.learning_objectives"
      ],
      "fr": [
        "scenario_info.title",
        "scenario_info.description",
        "scenario_info.prerequisites",
        "scenario_info.learning_objectives"
      ],
      "de": [
        "scenario_info.title",
        "scenario_info.description",
        "scenario_info.prerequisites",
        "scenario_info.learning_objectives"
      ],
      "it": [
        "scenario_info.title",
        "scenario_info.description",
        "scenario_info.prerequisites",
        "scenario_info.learning_objectives"
      ],
      "pt": [
        "tasks[0].title",
        "tasks[0].description",
        "tasks[0].instructions",
        "tasks[0].expected_outcome",
        "tasks[1].title",
        "tasks[1].description",
        "tasks[1].instructions",
        "tasks[1].expected_outcome",
        "tasks[2].title",
        "tasks[2].description",
        "tasks[2].instructions",
        "tasks[2].expected_outcome",
        "tasks[3].title",
        "tasks[3].description",
        "tasks[3].instructions",
        "tasks[3].expected_outcome"
      ],
      "ru": [
        "scenario_info.title",
        "scenario_info.description",
        "scenario_info.prerequisites",
        "scenario_info.learning_objectives"
      ],
      "ar": [
        "tasks[0].title",
        "tasks[0].description",
        "tasks[0].instructions",
        "tasks[0].expected_outcome",
        "tasks[1].title",
        "tasks[1].description",
        "tasks[1].instructions",
        "tasks[1].expected_outcome",
        "tasks[2].title",
        "tasks[2].description",
        "tasks[2].instructions",
        "tasks[2].expected_outcome",
        "tasks[3].title",
        "tasks[3].description",
        "tasks[3].instructions",
        "tasks[3].expected_outcome"
      ],
      "th": [
        "tasks[0].title",
        "tasks[0].description",
        "tasks[0].instructions",
        "tasks[0].expected_outcome",
        "tasks[1].title",
        "tasks[1].description",
        "tasks[1].instructions",
        "tasks[1].expected_outcome",
        "tasks[2].title",
        "tasks[2].description",
        "tasks[2].instructions",
        "tasks[2].expected_outcome",
        "tasks[3].title",
        "tasks[3].description",
        "tasks[3].instructions",
        "tasks[3].expected_outcome"
      ],
      "id": [
        "tasks[0].title",
        "tasks[0].description",
        "tasks[0].instructions",
        "tasks[0].expected_outcome",
        "tasks[1].title",
        "tasks[1].description",
        "tasks[1].instructions",
        "tasks[1].expected_outcome",
        "tasks[2].title",
        "tasks[2].description",
        "tasks[2].instructions",
        "tasks[2].expected_outcome",
        "tasks[3].title",
        "tasks[3].description",
        "tasks[3].instructions",
        "tasks[3].expected_outcome"
      ]
    },
    "missing_files": []
  },
  "high_school_creative_arts": {
    "translation_status": {
      "zhTW": {
        "total_fields": 16,
        "translated_fields": 12,
        "untranslated_fields": 4,
        "translation_rate": 75.0
      },
      "zhCN": {
        "total_fields": 16,
        "translated_fields": 4,
        "untranslated_fields": 12,
        "translation_rate": 25.0
      },
      "ja": {
        "total_fields": 16,
        "translated_fields": 12,
        "untranslated_fields": 4,
        "translation_rate": 75.0
      },
      "ko": {
        "total_fields": 16,
        "translated_fields": 12,
        "untranslated_fields": 4,
        "translation_rate": 75.0
      },
      "es": {
        "total_fields": 16,
        "translated_fields": 12,
        "untranslated_fields": 4,
        "translation_rate": 75.0
      },
      "fr": {
        "total_fields": 16,
        "translated_fields": 12,
        "untranslated_fields": 4,
        "translation_rate": 75.0
      },
      "de": {
        "total_fields": 16,
        "translated_fields": 12,
        "untranslated_fields": 4,
        "translation_rate": 75.0
      },
      "it": {
        "total_fields": 16,
        "translated_fields": 12,
        "untranslated_fields": 4,
        "translation_rate": 75.0
      },
      "pt": {
        "total_fields": 16,
        "translated_fields": 4,
        "untranslated_fields": 12,
        "translation_rate": 25.0
      },
      "ru": {
        "total_fields": 16,
        "translated_fields": 12,
        "untranslated_fields": 4,
        "translation_rate": 75.0
      },
      "ar": {
        "total_fields": 16,
        "translated_fields": 4,
        "untranslated_fields": 12,
        "translation_rate": 25.0
      },
      "th": {
        "total_fields": 16,
        "translated_fields": 4,
        "untranslated_fields": 12,
        "translation_rate": 25.0
      },
      "id": {
        "total_fields": 16,
        "translated_fields": 4,
        "untranslated_fields": 12,
        "translation_rate": 25.0
      }
    },
    "untranslated_fields": {
      "zhTW": [
        "scenario_info.title",
        "scenario_info.description",
        "scenario_info.prerequisites",
        "scenario_info.learning_objectives"
      ],
      "zhCN": [
        "tasks[0].title",
        "tasks[0].description",
        "tasks[0].instructions",
        "tasks[0].expected_outcome",
        "tasks[1].title",
        "tasks[1].description",
        "tasks[1].instructions",
        "tasks[1].expected_outcome",
        "tasks[2].title",
        "tasks[2].description",
        "tasks[2].instructions",
        "tasks[2].expected_outcome"
      ],
      "ja": [
        "scenario_info.title",
        "scenario_info.description",
        "scenario_info.prerequisites",
        "scenario_info.learning_objectives"
      ],
      "ko": [
        "scenario_info.title",
        "scenario_info.description",
        "scenario_info.prerequisites",
        "scenario_info.learning_objectives"
      ],
      "es": [
        "scenario_info.title",
        "scenario_info.description",
        "scenario_info.prerequisites",
        "scenario_info.learning_objectives"
      ],
      "fr": [
        "scenario_info.title",
        "scenario_info.description",
        "scenario_info.prerequisites",
        "scenario_info.learning_objectives"
      ],
      "de": [
        "scenario_info.title",
        "scenario_info.description",
        "scenario_info.prerequisites",
        "scenario_info.learning_objectives"
      ],
      "it": [
        "scenario_info.title",
        "scenario_info.description",
        "scenario_info.prerequisites",
        "scenario_info.learning_objectives"
      ],
      "pt": [
        "tasks[0].title",
        "tasks[0].description",
        "tasks[0].instructions",
        "tasks[0].expected_outcome",
        "tasks[1].title",
        "tasks[1].description",
        "tasks[1].instructions",
        "tasks[1].expected_outcome",
        "tasks[2].title",
        "tasks[2].description",
        "tasks[2].instructions",
        "tasks[2].expected_outcome"
      ],
      "ru": [
        "scenario_info.title",
        "scenario_info.description",
        "scenario_info.prerequisites",
        "scenario_info.learning_objectives"
      ],
      "ar": [
        "tasks[0].title",
        "tasks[0].description",
        "tasks[0].instructions",
        "tasks[0].expected_outcome",
        "tasks[1].title",
        "tasks[1].description",
        "tasks[1].instructions",
        "tasks[1].expected_outcome",
        "tasks[2].title",
        "tasks[2].description",
        "tasks[2].instructions",
        "tasks[2].expected_outcome"
      ],
      "th": [
        "tasks[0].title",
        "tasks[0].description",
        "tasks[0].instructions",
        "tasks[0].expected_outcome",
        "tasks[1].title",
        "tasks[1].description",
        "tasks[1].instructions",
        "tasks[1].expected_outcome",
        "tasks[2].title",
        "tasks[2].description",
        "tasks[2].instructions",
        "tasks[2].expected_outcome"
      ],
      "id": [
        "tasks[0].title",
        "tasks[0].description",
        "tasks[0].instructions",
        "tasks[0].expected_outcome",
        "tasks[1].title",
        "tasks[1].description",
        "tasks[1].instructions",
        "tasks[1].expected_outcome",
        "tasks[2].title",
        "tasks[2].description",
        "tasks[2].instructions",
        "tasks[2].expected_outcome"
      ]
    },
    "missing_files": []
  },
  "high_school_digital_wellness": {
    "translation_status": {
      "zhTW": {
        "total_fields": 24,
        "translated_fields": 20,
        "untranslated_fields": 4,
        "translation_rate": 83.3
      },
      "zhCN": {
        "total_fields": 24,
        "translated_fields": 4,
        "untranslated_fields": 20,
        "translation_rate": 16.7
      },
      "ja": {
        "total_fields": 24,
        "translated_fields": 20,
        "untranslated_fields": 4,
        "translation_rate": 83.3
      },
      "ko": {
        "total_fields": 24,
        "translated_fields": 20,
        "untranslated_fields": 4,
        "translation_rate": 83.3
      },
      "es": {
        "total_fields": 24,
        "translated_fields": 20,
        "untranslated_fields": 4,
        "translation_rate": 83.3
      },
      "fr": {
        "total_fields": 24,
        "translated_fields": 20,
        "untranslated_fields": 4,
        "translation_rate": 83.3
      },
      "de": {
        "total_fields": 24,
        "translated_fields": 20,
        "untranslated_fields": 4,
        "translation_rate": 83.3
      },
      "it": {
        "total_fields": 24,
        "translated_fields": 20,
        "untranslated_fields": 4,
        "translation_rate": 83.3
      },
      "pt": {
        "total_fields": 24,
        "translated_fields": 4,
        "untranslated_fields": 20,
        "translation_rate": 16.7
      },
      "ru": {
        "total_fields": 24,
        "translated_fields": 20,
        "untranslated_fields": 4,
        "translation_rate": 83.3
      },
      "ar": {
        "total_fields": 24,
        "translated_fields": 4,
        "untranslated_fields": 20,
        "translation_rate": 16.7
      },
      "th": {
        "total_fields": 24,
        "translated_fields": 4,
        "untranslated_fields": 20,
        "translation_rate": 16.7
      },
      "id": {
        "total_fields": 24,
        "translated_fields": 4,
        "untranslated_fields": 20,
        "translation_rate": 16.7
      }
    },
    "untranslated_fields": {
      "zhTW": [
        "scenario_info.title",
        "scenario_info.description",
        "scenario_info.prerequisites",
        "scenario_info.learning_objectives"
      ],
      "zhCN": [
        "tasks[0].title",
        "tasks[0].description",
        "tasks[0].instructions",
        "tasks[0].expected_outcome",
        "tasks[1].title",
        "tasks[1].description",
        "tasks[1].instructions",
        "tasks[1].expected_outcome",
        "tasks[2].title",
        "tasks[2].description",
        "tasks[2].instructions",
        "tasks[2].expected_outcome",
        "tasks[3].title",
        "tasks[3].description",
        "tasks[3].instructions",
        "tasks[3].expected_outcome",
        "tasks[4].title",
        "tasks[4].description",
        "tasks[4].instructions",
        "tasks[4].expected_outcome"
      ],
      "ja": [
        "scenario_info.title",
        "scenario_info.description",
        "scenario_info.prerequisites",
        "scenario_info.learning_objectives"
      ],
      "ko": [
        "scenario_info.title",
        "scenario_info.description",
        "scenario_info.prerequisites",
        "scenario_info.learning_objectives"
      ],
      "es": [
        "scenario_info.title",
        "scenario_info.description",
        "scenario_info.prerequisites",
        "scenario_info.learning_objectives"
      ],
      "fr": [
        "scenario_info.title",
        "scenario_info.description",
        "scenario_info.prerequisites",
        "scenario_info.learning_objectives"
      ],
      "de": [
        "scenario_info.title",
        "scenario_info.description",
        "scenario_info.prerequisites",
        "scenario_info.learning_objectives"
      ],
      "it": [
        "scenario_info.title",
        "scenario_info.description",
        "scenario_info.prerequisites",
        "scenario_info.learning_objectives"
      ],
      "pt": [
        "tasks[0].title",
        "tasks[0].description",
        "tasks[0].instructions",
        "tasks[0].expected_outcome",
        "tasks[1].title",
        "tasks[1].description",
        "tasks[1].instructions",
        "tasks[1].expected_outcome",
        "tasks[2].title",
        "tasks[2].description",
        "tasks[2].instructions",
        "tasks[2].expected_outcome",
        "tasks[3].title",
        "tasks[3].description",
        "tasks[3].instructions",
        "tasks[3].expected_outcome",
        "tasks[4].title",
        "tasks[4].description",
        "tasks[4].instructions",
        "tasks[4].expected_outcome"
      ],
      "ru": [
        "scenario_info.title",
        "scenario_info.description",
        "scenario_info.prerequisites",
        "scenario_info.learning_objectives"
      ],
      "ar": [
        "tasks[0].title",
        "tasks[0].description",
        "tasks[0].instructions",
        "tasks[0].expected_outcome",
        "tasks[1].title",
        "tasks[1].description",
        "tasks[1].instructions",
        "tasks[1].expected_outcome",
        "tasks[2].title",
        "tasks[2].description",
        "tasks[2].instructions",
        "tasks[2].expected_outcome",
        "tasks[3].title",
        "tasks[3].description",
        "tasks[3].instructions",
        "tasks[3].expected_outcome",
        "tasks[4].title",
        "tasks[4].description",
        "tasks[4].instructions",
        "tasks[4].expected_outcome"
      ],
      "th": [
        "tasks[0].title",
        "tasks[0].description",
        "tasks[0].instructions",
        "tasks[0].expected_outcome",
        "tasks[1].title",
        "tasks[1].description",
        "tasks[1].instructions",
        "tasks[1].expected_outcome",
        "tasks[2].title",
        "tasks[2].description",
        "tasks[2].instructions",
        "tasks[2].expected_outcome",
        "tasks[3].title",
        "tasks[3].description",
        "tasks[3].instructions",
        "tasks[3].expected_outcome",
        "tasks[4].title",
        "tasks[4].description",
        "tasks[4].instructions",
        "tasks[4].expected_outcome"
      ],
      "id": [
        "tasks[0].title",
        "tasks[0].description",
        "tasks[0].instructions",
        "tasks[0].expected_outcome",
        "tasks[1].title",
        "tasks[1].description",
        "tasks[1].instructions",
        "tasks[1].expected_outcome",
        "tasks[2].title",
        "tasks[2].description",
        "tasks[2].instructions",
        "tasks[2].expected_outcome",
        "tasks[3].title",
        "tasks[3].description",
        "tasks[3].instructions",
        "tasks[3].expected_outcome",
        "tasks[4].title",
        "tasks[4].description",
        "tasks[4].instructions",
        "tasks[4].expected_outcome"
      ]
    },
    "missing_files": []
  },
  "high_school_health_assistant": {
    "translation_status": {
      "zhTW": {
        "total_fields": 20,
        "translated_fields": 16,
        "untranslated_fields": 4,
        "translation_rate": 80.0
      },
      "zhCN": {
        "total_fields": 20,
        "translated_fields": 4,
        "untranslated_fields": 16,
        "translation_rate": 20.0
      },
      "ja": {
        "total_fields": 20,
        "translated_fields": 16,
        "untranslated_fields": 4,
        "translation_rate": 80.0
      },
      "ko": {
        "total_fields": 20,
        "translated_fields": 16,
        "untranslated_fields": 4,
        "translation_rate": 80.0
      },
      "es": {
        "total_fields": 20,
        "translated_fields": 16,
        "untranslated_fields": 4,
        "translation_rate": 80.0
      },
      "fr": {
        "total_fields": 20,
        "translated_fields": 16,
        "untranslated_fields": 4,
        "translation_rate": 80.0
      },
      "de": {
        "total_fields": 20,
        "translated_fields": 16,
        "untranslated_fields": 4,
        "translation_rate": 80.0
      },
      "it": {
        "total_fields": 20,
        "translated_fields": 16,
        "untranslated_fields": 4,
        "translation_rate": 80.0
      },
      "pt": {
        "total_fields": 20,
        "translated_fields": 4,
        "untranslated_fields": 16,
        "translation_rate": 20.0
      },
      "ru": {
        "total_fields": 20,
        "translated_fields": 16,
        "untranslated_fields": 4,
        "translation_rate": 80.0
      },
      "ar": {
        "total_fields": 20,
        "translated_fields": 4,
        "untranslated_fields": 16,
        "translation_rate": 20.0
      },
      "th": {
        "total_fields": 20,
        "translated_fields": 4,
        "untranslated_fields": 16,
        "translation_rate": 20.0
      },
      "id": {
        "total_fields": 20,
        "translated_fields": 4,
        "untranslated_fields": 16,
        "translation_rate": 20.0
      }
    },
    "untranslated_fields": {
      "zhTW": [
        "scenario_info.title",
        "scenario_info.description",
        "scenario_info.prerequisites",
        "scenario_info.learning_objectives"
      ],
      "zhCN": [
        "tasks[0].title",
        "tasks[0].description",
        "tasks[0].instructions",
        "tasks[0].expected_outcome",
        "tasks[1].title",
        "tasks[1].description",
        "tasks[1].instructions",
        "tasks[1].expected_outcome",
        "tasks[2].title",
        "tasks[2].description",
        "tasks[2].instructions",
        "tasks[2].expected_outcome",
        "tasks[3].title",
        "tasks[3].description",
        "tasks[3].instructions",
        "tasks[3].expected_outcome"
      ],
      "ja": [
        "scenario_info.title",
        "scenario_info.description",
        "scenario_info.prerequisites",
        "scenario_info.learning_objectives"
      ],
      "ko": [
        "scenario_info.title",
        "scenario_info.description",
        "scenario_info.prerequisites",
        "scenario_info.learning_objectives"
      ],
      "es": [
        "scenario_info.title",
        "scenario_info.description",
        "scenario_info.prerequisites",
        "scenario_info.learning_objectives"
      ],
      "fr": [
        "scenario_info.title",
        "scenario_info.description",
        "scenario_info.prerequisites",
        "scenario_info.learning_objectives"
      ],
      "de": [
        "scenario_info.title",
        "scenario_info.description",
        "scenario_info.prerequisites",
        "scenario_info.learning_objectives"
      ],
      "it": [
        "scenario_info.title",
        "scenario_info.description",
        "scenario_info.prerequisites",
        "scenario_info.learning_objectives"
      ],
      "pt": [
        "tasks[0].title",
        "tasks[0].description",
        "tasks[0].instructions",
        "tasks[0].expected_outcome",
        "tasks[1].title",
        "tasks[1].description",
        "tasks[1].instructions",
        "tasks[1].expected_outcome",
        "tasks[2].title",
        "tasks[2].description",
        "tasks[2].instructions",
        "tasks[2].expected_outcome",
        "tasks[3].title",
        "tasks[3].description",
        "tasks[3].instructions",
        "tasks[3].expected_outcome"
      ],
      "ru": [
        "scenario_info.title",
        "scenario_info.description",
        "scenario_info.prerequisites",
        "scenario_info.learning_objectives"
      ],
      "ar": [
        "tasks[0].title",
        "tasks[0].description",
        "tasks[0].instructions",
        "tasks[0].expected_outcome",
        "tasks[1].title",
        "tasks[1].description",
        "tasks[1].instructions",
        "tasks[1].expected_outcome",
        "tasks[2].title",
        "tasks[2].description",
        "tasks[2].instructions",
        "tasks[2].expected_outcome",
        "tasks[3].title",
        "tasks[3].description",
        "tasks[3].instructions",
        "tasks[3].expected_outcome"
      ],
      "th": [
        "tasks[0].title",
        "tasks[0].description",
        "tasks[0].instructions",
        "tasks[0].expected_outcome",
        "tasks[1].title",
        "tasks[1].description",
        "tasks[1].instructions",
        "tasks[1].expected_outcome",
        "tasks[2].title",
        "tasks[2].description",
        "tasks[2].instructions",
        "tasks[2].expected_outcome",
        "tasks[3].title",
        "tasks[3].description",
        "tasks[3].instructions",
        "tasks[3].expected_outcome"
      ],
      "id": [
        "tasks[0].title",
        "tasks[0].description",
        "tasks[0].instructions",
        "tasks[0].expected_outcome",
        "tasks[1].title",
        "tasks[1].description",
        "tasks[1].instructions",
        "tasks[1].expected_outcome",
        "tasks[2].title",
        "tasks[2].description",
        "tasks[2].instructions",
        "tasks[2].expected_outcome",
        "tasks[3].title",
        "tasks[3].description",
        "tasks[3].instructions",
        "tasks[3].expected_outcome"
      ]
    },
    "missing_files": []
  },
  "high_school_smart_city": {
    "translation_status": {
      "zhTW": {
        "total_fields": 24,
        "translated_fields": 20,
        "untranslated_fields": 4,
        "translation_rate": 83.3
      },
      "zhCN": {
        "total_fields": 24,
        "translated_fields": 4,
        "untranslated_fields": 20,
        "translation_rate": 16.7
      },
      "ja": {
        "total_fields": 24,
        "translated_fields": 20,
        "untranslated_fields": 4,
        "translation_rate": 83.3
      },
      "ko": {
        "total_fields": 24,
        "translated_fields": 20,
        "untranslated_fields": 4,
        "translation_rate": 83.3
      },
      "es": {
        "total_fields": 24,
        "translated_fields": 20,
        "untranslated_fields": 4,
        "translation_rate": 83.3
      },
      "fr": {
        "total_fields": 24,
        "translated_fields": 20,
        "untranslated_fields": 4,
        "translation_rate": 83.3
      },
      "de": {
        "total_fields": 24,
        "translated_fields": 20,
        "untranslated_fields": 4,
        "translation_rate": 83.3
      },
      "it": {
        "total_fields": 24,
        "translated_fields": 20,
        "untranslated_fields": 4,
        "translation_rate": 83.3
      },
      "pt": {
        "total_fields": 24,
        "translated_fields": 4,
        "untranslated_fields": 20,
        "translation_rate": 16.7
      },
      "ru": {
        "total_fields": 24,
        "translated_fields": 20,
        "untranslated_fields": 4,
        "translation_rate": 83.3
      },
      "ar": {
        "total_fields": 24,
        "translated_fields": 4,
        "untranslated_fields": 20,
        "translation_rate": 16.7
      },
      "th": {
        "total_fields": 24,
        "translated_fields": 4,
        "untranslated_fields": 20,
        "translation_rate": 16.7
      },
      "id": {
        "total_fields": 24,
        "translated_fields": 4,
        "untranslated_fields": 20,
        "translation_rate": 16.7
      }
    },
    "untranslated_fields": {
      "zhTW": [
        "scenario_info.title",
        "scenario_info.description",
        "scenario_info.prerequisites",
        "scenario_info.learning_objectives"
      ],
      "zhCN": [
        "tasks[0].title",
        "tasks[0].description",
        "tasks[0].instructions",
        "tasks[0].expected_outcome",
        "tasks[1].title",
        "tasks[1].description",
        "tasks[1].instructions",
        "tasks[1].expected_outcome",
        "tasks[2].title",
        "tasks[2].description",
        "tasks[2].instructions",
        "tasks[2].expected_outcome",
        "tasks[3].title",
        "tasks[3].description",
        "tasks[3].instructions",
        "tasks[3].expected_outcome",
        "tasks[4].title",
        "tasks[4].description",
        "tasks[4].instructions",
        "tasks[4].expected_outcome"
      ],
      "ja": [
        "scenario_info.title",
        "scenario_info.description",
        "scenario_info.prerequisites",
        "scenario_info.learning_objectives"
      ],
      "ko": [
        "scenario_info.title",
        "scenario_info.description",
        "scenario_info.prerequisites",
        "scenario_info.learning_objectives"
      ],
      "es": [
        "scenario_info.title",
        "scenario_info.description",
        "scenario_info.prerequisites",
        "scenario_info.learning_objectives"
      ],
      "fr": [
        "scenario_info.title",
        "scenario_info.description",
        "scenario_info.prerequisites",
        "scenario_info.learning_objectives"
      ],
      "de": [
        "scenario_info.title",
        "scenario_info.description",
        "scenario_info.prerequisites",
        "scenario_info.learning_objectives"
      ],
      "it": [
        "scenario_info.title",
        "scenario_info.description",
        "scenario_info.prerequisites",
        "scenario_info.learning_objectives"
      ],
      "pt": [
        "tasks[0].title",
        "tasks[0].description",
        "tasks[0].instructions",
        "tasks[0].expected_outcome",
        "tasks[1].title",
        "tasks[1].description",
        "tasks[1].instructions",
        "tasks[1].expected_outcome",
        "tasks[2].title",
        "tasks[2].description",
        "tasks[2].instructions",
        "tasks[2].expected_outcome",
        "tasks[3].title",
        "tasks[3].description",
        "tasks[3].instructions",
        "tasks[3].expected_outcome",
        "tasks[4].title",
        "tasks[4].description",
        "tasks[4].instructions",
        "tasks[4].expected_outcome"
      ],
      "ru": [
        "scenario_info.title",
        "scenario_info.description",
        "scenario_info.prerequisites",
        "scenario_info.learning_objectives"
      ],
      "ar": [
        "tasks[0].title",
        "tasks[0].description",
        "tasks[0].instructions",
        "tasks[0].expected_outcome",
        "tasks[1].title",
        "tasks[1].description",
        "tasks[1].instructions",
        "tasks[1].expected_outcome",
        "tasks[2].title",
        "tasks[2].description",
        "tasks[2].instructions",
        "tasks[2].expected_outcome",
        "tasks[3].title",
        "tasks[3].description",
        "tasks[3].instructions",
        "tasks[3].expected_outcome",
        "tasks[4].title",
        "tasks[4].description",
        "tasks[4].instructions",
        "tasks[4].expected_outcome"
      ],
      "th": [
        "tasks[0].title",
        "tasks[0].description",
        "tasks[0].instructions",
        "tasks[0].expected_outcome",
        "tasks[1].title",
        "tasks[1].description",
        "tasks[1].instructions",
        "tasks[1].expected_outcome",
        "tasks[2].title",
        "tasks[2].description",
        "tasks[2].instructions",
        "tasks[2].expected_outcome",
        "tasks[3].title",
        "tasks[3].description",
        "tasks[3].instructions",
        "tasks[3].expected_outcome",
        "tasks[4].title",
        "tasks[4].description",
        "tasks[4].instructions",
        "tasks[4].expected_outcome"
      ],
      "id": [
        "tasks[0].title",
        "tasks[0].description",
        "tasks[0].instructions",
        "tasks[0].expected_outcome",
        "tasks[1].title",
        "tasks[1].description",
        "tasks[1].instructions",
        "tasks[1].expected_outcome",
        "tasks[2].title",
        "tasks[2].description",
        "tasks[2].instructions",
        "tasks[2].expected_outcome",
        "tasks[3].title",
        "tasks[3].description",
        "tasks[3].instructions",
        "tasks[3].expected_outcome",
        "tasks[4].title",
        "tasks[4].description",
        "tasks[4].instructions",
        "tasks[4].expected_outcome"
      ]
    },
    "missing_files": []
  },
  "semiconductor_adventure": {
    "translation_status": {
      "zhTW": {
        "total_fields": 24,
        "translated_fields": 20,
        "untranslated_fields": 4,
        "translation_rate": 83.3
      },
      "zhCN": {
        "total_fields": 24,
        "translated_fields": 20,
        "untranslated_fields": 4,
        "translation_rate": 83.3
      },
      "ja": {
        "total_fields": 24,
        "translated_fields": 20,
        "untranslated_fields": 4,
        "translation_rate": 83.3
      },
      "ko": {
        "total_fields": 24,
        "translated_fields": 20,
        "untranslated_fields": 4,
        "translation_rate": 83.3
      },
      "es": {
        "total_fields": 24,
        "translated_fields": 20,
        "untranslated_fields": 4,
        "translation_rate": 83.3
      },
      "fr": {
        "total_fields": 24,
        "translated_fields": 20,
        "untranslated_fields": 4,
        "translation_rate": 83.3
      },
      "de": {
        "total_fields": 24,
        "translated_fields": 20,
        "untranslated_fields": 4,
        "translation_rate": 83.3
      },
      "it": {
        "total_fields": 24,
        "translated_fields": 20,
        "untranslated_fields": 4,
        "translation_rate": 83.3
      },
      "pt": {
        "total_fields": 24,
        "translated_fields": 20,
        "untranslated_fields": 4,
        "translation_rate": 83.3
      },
      "ru": {
        "total_fields": 24,
        "translated_fields": 20,
        "untranslated_fields": 4,
        "translation_rate": 83.3
      },
      "ar": {
        "total_fields": 24,
        "translated_fields": 20,
        "untranslated_fields": 4,
        "translation_rate": 83.3
      },
      "th": {
        "total_fields": 24,
        "translated_fields": 20,
        "untranslated_fields": 4,
        "translation_rate": 83.3
      },
      "id": {
        "total_fields": 24,
        "translated_fields": 20,
        "untranslated_fields": 4,
        "translation_rate": 83.3
      }
    },
    "untranslated_fields": {
      "zhTW": [
        "scenario_info.title",
        "scenario_info.description",
        "scenario_info.prerequisites",
        "scenario_info.learning_objectives"
      ],
      "zhCN": [
        "scenario_info.title",
        "scenario_info.description",
        "scenario_info.prerequisites",
        "scenario_info.learning_objectives"
      ],
      "ja": [
        "scenario_info.title",
        "scenario_info.description",
        "scenario_info.prerequisites",
        "scenario_info.learning_objectives"
      ],
      "ko": [
        "scenario_info.title",
        "scenario_info.description",
        "scenario_info.prerequisites",
        "scenario_info.learning_objectives"
      ],
      "es": [
        "scenario_info.title",
        "scenario_info.description",
        "scenario_info.prerequisites",
        "scenario_info.learning_objectives"
      ],
      "fr": [
        "scenario_info.title",
        "scenario_info.description",
        "scenario_info.prerequisites",
        "scenario_info.learning_objectives"
      ],
      "de": [
        "scenario_info.title",
        "scenario_info.description",
        "scenario_info.prerequisites",
        "scenario_info.learning_objectives"
      ],
      "it": [
        "scenario_info.title",
        "scenario_info.description",
        "scenario_info.prerequisites",
        "scenario_info.learning_objectives"
      ],
      "pt": [
        "scenario_info.title",
        "scenario_info.description",
        "scenario_info.prerequisites",
        "scenario_info.learning_objectives"
      ],
      "ru": [
        "scenario_info.title",
        "scenario_info.description",
        "scenario_info.prerequisites",
        "scenario_info.learning_objectives"
      ],
      "ar": [
        "scenario_info.title",
        "scenario_info.description",
        "scenario_info.prerequisites",
        "scenario_info.learning_objectives"
      ],
      "th": [
        "scenario_info.title",
        "scenario_info.description",
        "scenario_info.prerequisites",
        "scenario_info.learning_objectives"
      ],
      "id": [
        "scenario_info.title",
        "scenario_info.description",
        "scenario_info.prerequisites",
        "scenario_info.learning_objectives"
      ]
    },
    "missing_files": []
  }
}